StrucPy/RCFA.py
StrucPy/_RCSingle.py
StrucPy/__init__.py
StrucPy/_arrangeCal.py
StrucPy/_forcesCal.py
StrucPy-0.0.1.dist-info/LICENSE
StrucPy-0.0.1.dist-info/METADATA
StrucPy-0.0.1.dist-info/WHEEL
StrucPy-0.0.1.dist-info/top_level.txt
StrucPy-0.0.1.dist-info/RECORD
