Metadata-Version: 2.1
Name: StrucPy
Version: 0.0.1
Summary: Object Oriented Structural Analysis
Home-page: https://github.com/TabishIzhar/StrucPy.git
Author: Tabish Izhar
Author-email: tizhar@iul.ac.in
License: GNU LGPLv2.1
Project-URL: Bug Tracker, https://github.com/TabishIzhar/StrucPy/issues
Classifier: Programming Language :: Python :: 3.10
Classifier: Operating System :: OS Independent
Requires-Python: >=3.9
License-File: LICENSE
Requires-Dist: numpy ==1.23.3
Requires-Dist: openpyxl ==3.0.10
Requires-Dist: pandas ==1.4.4
Requires-Dist: plotly ==5.10.0
Requires-Dist: ray ==2.6.1
